setup.py
./test/__init__.py
./test/helpers.py
./test/test_covtype.py
./test/test_diabetes_classify.py
./test/test_digits.py
./test/test_iris.py
cudatree/__init__.py
cudatree/base_tree.py
cudatree/datasource.py
cudatree/random_forest.py
cudatree/random_tree.py
cudatree/util.py
cudatree.egg-info/PKG-INFO
cudatree.egg-info/SOURCES.txt
cudatree.egg-info/dependency_links.txt
cudatree.egg-info/requires.txt
cudatree.egg-info/top_level.txt
cudatree/cuda_kernels/bfs_module.cu
cudatree/cuda_kernels/bootstrap_fill.cu
cudatree/cuda_kernels/bootstrap_reshuffle.cu
cudatree/cuda_kernels/common_func.cu
cudatree/cuda_kernels/dfs_module.cu
cudatree/cuda_kernels/feature_selector.cu
cudatree/cuda_kernels/predict.cu
hybridforest/__init__.py
hybridforest/builder.py
hybridforest/hybridforest.py
test/__init__.py
test/helpers.py
test/test_covtype.py
test/test_diabetes_classify.py
test/test_digits.py
test/test_iris.py