Metadata-Version: 1.1
Name: cudatree
Version: 0.6
Summary: Random Forests for the GPU using PyCUDA
Home-page: https://github.com/EasonLiao/CudaTree
Author: Yisheng Liao and Alex Rubinsteyn
Author-email: ['yl1912@nyu.edu / alexr@cs.nyu.edu']
License: BSD
Platform: UNKNOWN
Classifier: Development Status :: 3 - Alpha
Classifier: Topic :: Software Development :: Libraries
Classifier: Topic :: Scientific/Engineering
Classifier: License :: OSI Approved :: BSD License
Classifier: Intended Audience :: Developers
Classifier: Intended Audience :: Science/Research
Classifier: Programming Language :: Python :: 2.7
